emailservice.py
src/__init__.py
src/emailservice.py
emailservice-0.0.5.dist-info/METADATA
emailservice-0.0.5.dist-info/WHEEL
emailservice-0.0.5.dist-info/top_level.txt
emailservice-0.0.5.dist-info/RECORD
